workback/__init__.py
workback/main.py
workback/tools/__init__.py
workback/tools/analysis_context.py
workback/tools/analysis_tools.py
workback/tools/claude_client.py
workback/tools/logger.py
workback/tui/__init__.py
workback/tui/app.py
workback/tui/styles.css
workback-0.1.3.dist-info/METADATA
workback-0.1.3.dist-info/WHEEL
workback-0.1.3.dist-info/entry_points.txt
workback-0.1.3.dist-info/licenses/LICENSE
workback-0.1.3.dist-info/RECORD
